README.md
setup.py
runthis/server/__init__.py
runthis/server/__main__.py
runthis/server/config.py
runthis/server/hypercorn.py
runthis/server/langs.py
runthis/server/main.py
runthis_server.egg-info/PKG-INFO
runthis_server.egg-info/SOURCES.txt
runthis_server.egg-info/dependency_links.txt
runthis_server.egg-info/not-zip-safe
runthis_server.egg-info/requires.txt
runthis_server.egg-info/top_level.txt
scripts/runthis-server