Metadata-Version: 2.1
Name: runthis-server
Version: 0.0.4
Summary: Safely serves multiple, isolated terminal sessions in a browser
Home-page: https://github.com/regro/runthis-server
Author: Anthony Scopatz
Author-email: scopatz@gmail.com
Maintainer: Anthony Scopatz
License: BSD
Platform: Cross Platform
Classifier: Programming Language :: Python :: 3
Requires-Python: >=3.6
